{
  "openapi": "3.0.0",
  "info": {
    "title": "API Documentation",
    "version": "1.0.0"
  },
  "paths": {
    "/games": {
      "get": {
        "tags": [
          "Games"
        ],
        "summary": "Obtener lista de juegos",
        "responses": {
          "200": {
            "description": "OK",
            "content": {
              "application/json": {
                "schema": {
                  "type": "array",
                  "items": {
                    "$ref": "#/components/schemas/Game"
                  }
                }
              }
            }
          },
          "400": {
            "description": "Error de solicitud"
          }
        }
      },
      "post": {
        "tags": [
          "Games"
        ],
        "summary": "Crear un nuevo juego",
        "requestBody": {
          "required": true,
          "content": {
            "application/json": {
              "schema": {
                "$ref": "#/components/schemas/NewGame"
              }
            }
          }
        },
        "responses": {
          "201": {
            "description": "Juego creado exitosamente",
            "content": {
              "application/json": {
                "schema": {
                  "$ref": "#/components/schemas/Game"
                }
              }
            }
          },
          "400": {
            "description": "Error de solicitud"
          }
        }
      }
    },
    "/games/{id}": {
      "get": {
        "tags": [
          "Games"
        ],
        "summary": "Obtener detalles de un juego específico",
        "parameters": [
          {
            "name": "id",
            "in": "path",
            "description": "ID del juego",
            "required": true,
            "schema": {
              "type": "integer"
            }
          }
        ],
        "responses": {
          "200": {
            "description": "OK",
            "content": {
              "application/json": {
                "schema": {
                  "$ref": "#/components/schemas/Game"
                }
              }
            }
          },
          "400": {
            "description": "Error de solicitud"
          }
        }
      },
      "patch": {
        "tags": [
          "Games"
        ],
        "summary": "Actualizar un juego existente",
        "parameters": [
          {
            "name": "id",
            "in": "path",
            "description": "ID del juego",
            "required": true,
            "schema": {
              "type": "integer"
            }
          }
        ],
        "requestBody": {
          "required": true,
          "content": {
            "application/json": {
              "schema": {
                "$ref": "#/components/schemas/UpdateGame"
              }
            }
          }
        },
        "responses": {
          "200": {
            "description": "Juego actualizado exitosamente",
            "content": {
              "application/json": {
                "schema": {
                  "$ref": "#/components/schemas/Game"
                }
              }
            }
          },
          "400": {
            "description": "Error de solicitud"
          }
        }
      },
      "delete": {
        "tags": [
          "Games"
        ],
        "summary": "Eliminar un juego existente",
        "parameters": [
          {
            "name": "id",
            "in": "path",
            "description": "ID del juego",
            "required": true,
            "schema": {
              "type": "integer"
            }
          }
        ],
        "responses": {
          "200": {
            "description": "Juego eliminado exitosamente",
            "content": {
              "application/json": {
                "schema": {
                  "$ref": "#/components/schemas/Game"
                }
              }
            }
          },
          "400": {
            "description": "Error de solicitud"
          }
        }
      }
    },
    "/users": {
      "get": {
        "tags": [
          "Users"
        ],
        "summary": "Obtener lista de usuarios",
        "responses": {
          "200": {
            "description": "OK",
            "content": {
              "application/json": {
                "schema": {
                  "type": "array",
                  "items": {
                    "$ref": "#/components/schemas/User"
                  }
                }
              }
            }
          },
          "400": {
            "description": "Error de solicitud"
          }
        }
      },
      "post": {
        "tags": [
          "Users"
        ],
        "summary": "Crear un nuevo usuario",
        "requestBody": {
          "required": true,
          "content": {
            "application/json": {
              "schema": {
                "$ref": "#/components/schemas/NewUser"
              }
            }
          }
        },
        "responses": {
          "201": {
            "description": "Usuario creado exitosamente",
            "content": {
              "application/json": {
                "schema": {
                  "$ref": "#/components/schemas/User"
                }
              }
            }
          },
          "400": {
            "description": "Error de solicitud"
          }
        }
      }
    },
    "/users/{id}": {
      "get": {
        "tags": [
          "Users"
        ],
        "summary": "Obtener detalles de un usuario específico",
        "parameters": [
          {
            "name": "id",
            "in": "path",
            "description": "ID del usuario",
            "required": true,
            "schema": {
              "type": "integer"
            }
          }
        ],
        "responses": {
          "200": {
            "description": "OK",
            "content": {
              "application/json": {
                "schema": {
                  "$ref": "#/components/schemas/User"
                }
              }
            }
          },
          "400": {
            "description": "Error de solicitud"
          }
        }
      },
      "patch": {
        "tags": [
          "Users"
        ],
        "summary": "Actualizar un usuario existente",
        "parameters": [
          {
            "name": "id",
            "in": "path",
            "description": "ID del usuario",
            "required": true,
            "schema": {
              "type": "integer"
            }
          }
        ],
        "requestBody": {
          "required": true,
          "content": {
            "application/json": {
              "schema": {
                "$ref": "#/components/schemas/UpdateUser"
              }
            }
          }
        },
        "responses": {
          "200": {
            "description": "Usuario actualizado exitosamente",
            "content": {
              "application/json": {
                "schema": {
                  "$ref": "#/components/schemas/User"
                }
              }
            }
          },
          "400": {
            "description": "Error de solicitud"
          }
        }
      },
      "delete": {
        "tags": [
          "Users"
        ],
        "summary": "Eliminar un usuario existente",
        "parameters": [
          {
            "name": "id",
            "in": "path",
            "description": "ID del usuario",
            "required": true,
            "schema": {
              "type": "integer"
            }
          }
        ],
        "responses": {
          "200": {
            "description": "Usuario eliminado exitosamente",
            "content": {
              "application/json": {
                "schema": {
                  "$ref": "#/components/schemas/User"
                }
              }
            }
          },
          "400": {
            "description": "Error de solicitud"
          }
        }
      }
    },
    "/cells": {
      "get": {
        "tags": [
          "Cells"
        ],
        "summary": "Obtener lista de celdas",
        "responses": {
          "200": {
            "description": "OK",
            "content": {
              "application/json": {
                "schema": {
                  "type": "array",
                  "items": {
                    "$ref": "#/components/schemas/Cell"
                  }
                }
              }
            }
          },
          "400": {
            "description": "Error de solicitud"
          }
        }
      },
      "post": {
        "tags": [
          "Cells"
        ],
        "summary": "Crear una nueva celda",
        "requestBody": {
          "required": true,
          "content": {
            "application/json": {
              "schema": {
                "$ref": "#/components/schemas/NewCell"
              }
            }
          }
        },
        "responses": {
          "201": {
            "description": "Celda creada exitosamente",
            "content": {
              "application/json": {
                "schema": {
                  "$ref": "#/components/schemas/Cell"
                }
              }
            }
          },
          "400": {
            "description": "Error de solicitud"
          }
        }
      }
    },
    "/cells/{id}": {
      "get": {
        "tags": [
          "Cells"
        ],
        "summary": "Obtener detalles de una celda específica",
        "parameters": [
          {
            "name": "id",
            "in": "path",
            "description": "ID de la celda",
            "required": true,
            "schema": {
              "type": "integer"
            }
          }
        ],
        "responses": {
          "200": {
            "description": "OK",
            "content": {
              "application/json": {
                "schema": {
                  "$ref": "#/components/schemas/Cell"
                }
              }
            }
          },
          "400": {
            "description": "Error de solicitud"
          }
        }
      },
      "patch": {
        "tags": [
          "Cells"
        ],
        "summary": "Actualizar una celda existente",
        "parameters": [
          {
            "name": "id",
            "in": "path",
            "description": "ID de la celda",
            "required": true,
            "schema": {
              "type": "integer"
            }
          }
        ],
        "requestBody": {
          "required": true,
          "content": {
            "application/json": {
              "schema": {
                "$ref": "#/components/schemas/UpdateCell"
              }
            }
          }
        },
        "responses": {
          "200": {
            "description": "Celda actualizada exitosamente",
            "content": {
              "application/json": {
                "schema": {
                  "$ref": "#/components/schemas/Cell"
                }
              }
            }
          },
          "400": {
            "description": "Error de solicitud"
          }
        }
      },
      "delete": {
        "tags": [
          "Cells"
        ],
        "summary": "Eliminar una celda existente",
        "parameters": [
          {
            "name": "id",
            "in": "path",
            "description": "ID de la celda",
            "required": true,
            "schema": {
              "type": "integer"
            }
          }
        ],
        "responses": {
          "200": {
            "description": "Celda eliminada exitosamente",
            "content": {
              "application/json": {
                "schema": {
                  "$ref": "#/components/schemas/Cell"
                }
              }
            }
          },
          "400": {
            "description": "Error de solicitud"
          }
        }
      }
    },
    "/players": {
      "get": {
        "tags": [
          "Players"
        ],
        "summary": "Obtener lista de jugadores",
        "responses": {
          "200": {
            "description": "OK",
            "content": {
              "application/json": {
                "schema": {
                  "type": "array",
                  "items": {
                    "$ref": "#/components/schemas/Player"
                  }
                }
              }
            }
          },
          "400": {
            "description": "Error de solicitud"
          }
        }
      },
      "post": {
        "tags": [
          "Players"
        ],
        "summary": "Crear un nuevo jugador",
        "requestBody": {
          "required": true,
          "content": {
            "application/json": {
              "schema": {
                "$ref": "#/components/schemas/NewPlayer"
              }
            }
          }
        },
        "responses": {
          "201": {
            "description": "Jugador creado exitosamente",
            "content": {
              "application/json": {
                "schema": {
                  "$ref": "#/components/schemas/Player"
                }
              }
            }
          },
          "400": {
            "description": "Error de solicitud"
          }
        }
      }
    },
    "/players/{id}": {
      "get": {
        "tags": [
          "Players"
        ],
        "summary": "Obtener detalles de un jugador específico",
        "parameters": [
          {
            "name": "id",
            "in": "path",
            "description": "ID del jugador",
            "required": true,
            "schema": {
              "type": "integer"
            }
          }
        ],
        "responses": {
          "200": {
            "description": "OK",
            "content": {
              "application/json": {
                "schema": {
                  "$ref": "#/components/schemas/Player"
                }
              }
            }
          },
          "400": {
            "description": "Error de solicitud"
          }
        }
      },
      "patch": {
        "tags": [
          "Players"
        ],
        "summary": "Actualizar un jugador existente",
        "parameters": [
          {
            "name": "id",
            "in": "path",
            "description": "ID del jugador",
            "required": true,
            "schema": {
              "type": "integer"
            }
          }
        ],
        "requestBody": {
          "required": true,
          "content": {
            "application/json": {
              "schema": {
                "$ref": "#/components/schemas/UpdatePlayer"
              }
            }
          }
        },
        "responses": {
          "200": {
            "description": "Jugador actualizado exitosamente",
            "content": {
              "application/json": {
                "schema": {
                  "$ref": "#/components/schemas/Player"
                }
              }
            }
          },
          "400": {
            "description": "Error de solicitud"
          }
        }
      },
      "delete": {
        "tags": [
          "Players"
        ],
        "summary": "Eliminar un jugador existente",
        "parameters": [
          {
            "name": "id",
            "in": "path",
            "description": "ID del jugador",
            "required": true,
            "schema": {
              "type": "integer"
            }
          }
        ],
        "responses": {
          "200": {
            "description": "Jugador eliminado exitosamente",
            "content": {
              "application/json": {
                "schema": {
                  "$ref": "#/components/schemas/Player"
                }
              }
            }
          },
          "400": {
            "description": "Error de solicitud"
          }
        }
      }
    }
  },
  "components": {
    "schemas": {
      "Game": {
        "type": "object",
        "properties": {
          "id": {
            "type": "integer"
          },
          "name": {
            "type": "string"
          },
          "status": {
            "type": "integer"
          }
        },
        "required": [
          "name",
          "status"
        ]
      },
      "NewGame": {
        "type": "object",
        "properties": {
          "name": {
            "type": "string"
          },
          "status": {
            "type": "integer"
          }
        },
        "required": [
          "name",
          "status"
        ]
      },
      "UpdateGame": {
        "type": "object",
        "properties": {
          "name": {
            "type": "string"
          },
          "status": {
            "type": "integer"
          }
        }
      },
      "User": {
        "type": "object",
        "properties": {
          "id": {
            "type": "integer"
          },
          "name": {
            "type": "string"
          },
          "email": {
            "type": "string"
          }
        },
        "required": [
          "name",
          "email"
        ]
      },
      "NewUser": {
        "type": "object",
        "properties": {
          "name": {
            "type": "string"
          },
          "email": {
            "type": "string"
          }
        },
        "required": [
          "name",
          "email"
        ]
      },
      "UpdateUser": {
        "type": "object",
        "properties": {
          "name": {
            "type": "string"
          },
          "email": {
            "type": "string"
          }
        }
      },
      "Cell": {
        "type": "object",
        "properties": {
          "id": {
            "type": "integer"
          },
          "gameId": {
            "type": "integer"
          },
          "column": {
            "type": "integer"
          },
          "row": {
            "type": "integer"
          },
          "status": {
            "type": "integer"
          }
        },
        "required": [
          "gameId",
          "column",
          "row",
          "status"
        ]
      },
      "NewCell": {
        "type": "object",
        "properties": {
          "gameId": {
            "type": "integer"
          },
          "column": {
            "type": "integer"
          },
          "row": {
            "type": "integer"
          },
          "status": {
            "type": "integer"
          }
        },
        "required": [
          "gameId",
          "column",
          "row",
          "status"
        ]
      },
      "UpdateCell": {
        "type": "object",
        "properties": {
          "gameId": {
            "type": "integer"
          },
          "column": {
            "type": "integer"
          },
          "row": {
            "type": "integer"
          },
          "status": {
            "type": "integer"
          }
        }
      },
      "Player": {
        "type": "object",
        "properties": {
          "id": {
            "type": "integer"
          },
          "gameId": {
            "type": "integer"
          },
          "userId": {
            "type": "integer"
          }
        },
        "required": [
          "gameId",
          "userId"
        ]
      },
      "NewPlayer": {
        "type": "object",
        "properties": {
          "gameId": {
            "type": "integer"
          },
          "userId": {
            "type": "integer"
          }
        },
        "required": [
          "gameId",
          "userId"
        ]
      },
      "UpdatePlayer": {
        "type": "object",
        "properties": {
          "gameId": {
            "type": "integer"
          },
          "userId": {
            "type": "integer"
          }
        }
      }
    }
  }
}